README.rst
setup.py
thinserve/__init__.py
thinserve/util.py
thinserve.egg-info/PKG-INFO
thinserve.egg-info/SOURCES.txt
thinserve.egg-info/dependency_links.txt
thinserve.egg-info/requires.txt
thinserve.egg-info/top_level.txt
thinserve/api/__init__.py
thinserve/api/apiresource.py
thinserve/api/referenceable.py
thinserve/api/remerr.py
thinserve/api/resource.py
thinserve/api/site.py
thinserve/proto/__init__.py
thinserve/proto/error.py
thinserve/proto/lazyparser.py
thinserve/proto/session.py
thinserve/proto/shuttle.py
thinserve/tests/__init__.py
thinserve/tests/testutil.py
thinserve/tests/api/__init__.py
thinserve/tests/api/test_apiresource.py
thinserve/tests/api/test_referenceable.py
thinserve/tests/api/test_resource.py
thinserve/tests/api/test_site.py
thinserve/tests/proto/__init__.py
thinserve/tests/proto/test_lazyparser.py
thinserve/tests/proto/test_session.py
thinserve/tests/proto/test_shuttle.py