Metadata-Version: 1.0
Name: thinserve
Version: 0.1.dev1
Summary: A twisted thin server framework for JSON API + static html clients.
Home-page: https://github.com/nejucomo/thinserve
Author: Nathan Wilcox
Author-email: nejucomo@gmail.com
License: GPLv3
Platform: UNKNOWN
